AUTHORS
LICENSE
MANIFEST.in
README
setup.py
version.py
docs/source/conf.py
docs/source/index.rst
docs/source/intro.rst
docs/source/markup.rst
docs/source/signals.rst
docs/source/schema/arrays.rst
docs/source/schema/compound.rst
docs/source/schema/containers.rst
docs/source/schema/datetimes.rst
docs/source/schema/dicts.rst
docs/source/schema/enums.rst
docs/source/schema/forms.rst
docs/source/schema/index.rst
docs/source/schema/lists.rst
docs/source/schema/properties.rst
docs/source/schema/references.rst
docs/source/schema/scalars.rst
docs/source/schema/schema.rst
docs/source/schema/traversal.rst
docs/source/validation/index.rst
flatland/__init__.py
flatland/exc.py
flatland/signals.py
flatland/ext/__init__.py
flatland/ext/creditcard.py
flatland/i18n/flatland.pot
flatland/i18n/de/LC_MESSAGES/flatland.po
flatland/i18n/es/LC_MESSAGES/flatland.po
flatland/i18n/fr/LC_MESSAGES/flatland.po
flatland/out/__init__.py
flatland/out/generic.py
flatland/out/genshi.py
flatland/out/markup.py
flatland/out/util.py
flatland/schema/__init__.py
flatland/schema/base.py
flatland/schema/compound.py
flatland/schema/containers.py
flatland/schema/forms.py
flatland/schema/paths.py
flatland/schema/properties.py
flatland/schema/scalars.py
flatland/schema/util.py
flatland/util/__init__.py
flatland/util/base.py
flatland/util/deferred.py
flatland/validation/__init__.py
flatland/validation/base.py
flatland/validation/containers.py
flatland/validation/network.py
flatland/validation/number.py
flatland/validation/scalars.py
flatland/validation/string.py
flatland_fork.egg-info/PKG-INFO
flatland_fork.egg-info/SOURCES.txt
flatland_fork.egg-info/dependency_links.txt
flatland_fork.egg-info/requires.txt
flatland_fork.egg-info/top_level.txt
flatland_fork.egg-info/zip-safe
tests/__init__.py
tests/_util.py
tests/test_forms.py
tests/test_i18n.py
tests/test_richtypes.py
tests/test_schema.py
tests/test_utils.py
tests/test_validation.py
tests/markup/__init__.py
tests/markup/_util.py
tests/markup/test_context.py
tests/markup/test_generator.py
tests/markup/test_genshi.py
tests/markup/test_tag_context.py
tests/markup/test_tag_forcing.py
tests/markup/test_tag_pairing.py
tests/markup/test_tag_rendering.py
