Metadata-Version: 1.1
Name: flatland-fork
Version: 0.3
Summary: HTML form management and validation
Home-page: http://discorporate.us/jek/projects/flatland/
Author: Jason Kirtland
Author-email: jek@discorporate.us
License: MIT License
Keywords: schema validation data web form forms roundtrip
Platform: UNKNOWN
Classifier: Development Status :: 4 - Beta
Classifier: Environment :: Web Environment
Classifier: Intended Audience :: Developers
Classifier: License :: OSI Approved :: MIT License
Classifier: Natural Language :: English
Classifier: Operating System :: OS Independent
Classifier: Programming Language :: Python
Classifier: Programming Language :: Python :: 2.5
Classifier: Programming Language :: Python :: 2.6
Classifier: Programming Language :: Python :: 2.7
Classifier: Topic :: Internet :: WWW/HTTP :: WSGI
Classifier: Topic :: Software Development :: Libraries
